LICENSE.txt
README.md
setup.py
src/ExeLib/__init__.py
src/ExeLib.egg-info/PKG-INFO
src/ExeLib.egg-info/SOURCES.txt
src/ExeLib.egg-info/dependency_links.txt
src/ExeLib.egg-info/top_level.txt