Metadata-Version: 2.1
Name: ExeLib
Version: 1.0.1
Summary: An Alt To exec()..!!
Home-page: https://github.com/mastercodermerwin/ExeLib
Author: Cactochan
License: UNKNOWN
Project-URL: Bug Tracker, https://github.com/mastercodermerwin/ExeLib/issues
Platform: UNKNOWN
Classifier: Programming Language :: Python :: 3
Classifier: License :: OSI Approved :: MIT License
Classifier: Operating System :: OS Independent
License-File: LICENSE.txt
